pystuduino-1.0.0.dist-info/METADATA
pystuduino-1.0.0.dist-info/RECORD
pystuduino-1.0.0.dist-info/WHEEL
pystuduino-1.0.0.dist-info/entry_points.txt
pystuduino-1.0.0.dist-info/top_level.txt
studuino/__init__.py
studuino/bglib.py
studuino/ble_wrapper.py
studuino/command.py
studuino/connector.py
studuino/const.py
studuino/graph.py
studuino/part.py
studuino/sensor.py
studuino/upload.py
