Metadata-Version: 2.1
Name: pystuduino
Version: 1.0.0
Summary: Python library for Studuino&ArtecRobo
Home-page: https://github.com/artec-kk/pystuduino
Author: Artec Co., Ltd.
Author-email: support@artec-kk.co.jp
License: UNKNOWN
Platform: UNKNOWN
Requires-Dist: pyserial
Requires-Dist: numpy
Requires-Dist: matplotlib
